.gitignore
LICENSE.rst
README.rst
distribute_setup.py
requirements.txt
setup.cfg
setup.py
eadtoolbox/__init__.py
eadtoolbox/sandbox.py
eadtoolbox/transform.py
eadtoolbox/validate.py
eadtoolbox.egg-info/PKG-INFO
eadtoolbox.egg-info/SOURCES.txt
eadtoolbox.egg-info/dependency_links.txt
eadtoolbox.egg-info/entry_points.txt
eadtoolbox.egg-info/requires.txt
eadtoolbox.egg-info/top_level.txt
eadtoolbox/data/css/eadsandbox.css
eadtoolbox/data/html/head.tmpl
eadtoolbox/data/html/home.html
eadtoolbox/data/html/tail.tmpl
eadtoolbox/data/xml/ead.dtd
eadtoolbox/data/xml/ead2isadg.xsl
eadtoolbox/data/xml/ead2marcxml.xsl
eadtoolbox/data/xml/ead2oai_dc.xsl
eadtoolbox/data/xml/ead2srw_dc.xsl