Metadata-Version: 1.1
Name: eadtoolbox
Version: 1.0.0
Summary: Tools for working with EAD XML files.
Home-page: http://github.com/bloomonkey/ead-toolbox
Author: John Harrison
Author-email: john.harrison@liv.ac.uk
License: BSD
Platform: UNKNOWN
Classifier: Intended Audience :: Developers
Classifier: Intended Audience :: Information Technology
Classifier: License :: OSI Approved :: BSD License
Classifier: Programming Language :: Python :: 2.6
Classifier: Programming Language :: Python :: 2.7
Classifier: Topic :: Text Processing :: Markup
Classifier: Topic :: Internet :: WWW/HTTP :: WSGI :: Application
Requires: lxml(>=2.1)
Requires: wsgiref
